
{"items":[{"name":"wan24.ObjectValidation","href":"wan24.ObjectValidation.html","topicHref":"wan24.ObjectValidation.html","topicUid":"wan24.ObjectValidation","items":[{"name":"AbaFormats","href":"wan24.ObjectValidation.AbaFormats.html","topicHref":"wan24.ObjectValidation.AbaFormats.html","topicUid":"wan24.ObjectValidation.AbaFormats"},{"name":"AbaRtnAttribute","href":"wan24.ObjectValidation.AbaRtnAttribute.html","topicHref":"wan24.ObjectValidation.AbaRtnAttribute.html","topicUid":"wan24.ObjectValidation.AbaRtnAttribute"},{"name":"AbaValidation","href":"wan24.ObjectValidation.AbaValidation.html","topicHref":"wan24.ObjectValidation.AbaValidation.html","topicUid":"wan24.ObjectValidation.AbaValidation"},{"name":"AmountAttribute","href":"wan24.ObjectValidation.AmountAttribute.html","topicHref":"wan24.ObjectValidation.AmountAttribute.html","topicUid":"wan24.ObjectValidation.AmountAttribute"},{"name":"BicAttribute","href":"wan24.ObjectValidation.BicAttribute.html","topicHref":"wan24.ObjectValidation.BicAttribute.html","topicUid":"wan24.ObjectValidation.BicAttribute"},{"name":"CountLimitAttribute","href":"wan24.ObjectValidation.CountLimitAttribute.html","topicHref":"wan24.ObjectValidation.CountLimitAttribute.html","topicUid":"wan24.ObjectValidation.CountLimitAttribute"},{"name":"CountryAttribute","href":"wan24.ObjectValidation.CountryAttribute.html","topicHref":"wan24.ObjectValidation.CountryAttribute.html","topicUid":"wan24.ObjectValidation.CountryAttribute"},{"name":"CountryCodes","href":"wan24.ObjectValidation.CountryCodes.html","topicHref":"wan24.ObjectValidation.CountryCodes.html","topicUid":"wan24.ObjectValidation.CountryCodes"},{"name":"CurrencyAttribute","href":"wan24.ObjectValidation.CurrencyAttribute.html","topicHref":"wan24.ObjectValidation.CurrencyAttribute.html","topicUid":"wan24.ObjectValidation.CurrencyAttribute"},{"name":"CurrencyCodes","href":"wan24.ObjectValidation.CurrencyCodes.html","topicHref":"wan24.ObjectValidation.CurrencyCodes.html","topicUid":"wan24.ObjectValidation.CurrencyCodes"},{"name":"CurrencyCodes.Currency","href":"wan24.ObjectValidation.CurrencyCodes.Currency.html","topicHref":"wan24.ObjectValidation.CurrencyCodes.Currency.html","topicUid":"wan24.ObjectValidation.CurrencyCodes.Currency"},{"name":"CurrencyFormats","href":"wan24.ObjectValidation.CurrencyFormats.html","topicHref":"wan24.ObjectValidation.CurrencyFormats.html","topicUid":"wan24.ObjectValidation.CurrencyFormats"},{"name":"EuVatId","href":"wan24.ObjectValidation.EuVatId.html","topicHref":"wan24.ObjectValidation.EuVatId.html","topicUid":"wan24.ObjectValidation.EuVatId"},{"name":"EuVatIdAttribute","href":"wan24.ObjectValidation.EuVatIdAttribute.html","topicHref":"wan24.ObjectValidation.EuVatIdAttribute.html","topicUid":"wan24.ObjectValidation.EuVatIdAttribute"},{"name":"HostAttribute","href":"wan24.ObjectValidation.HostAttribute.html","topicHref":"wan24.ObjectValidation.HostAttribute.html","topicUid":"wan24.ObjectValidation.HostAttribute"},{"name":"ICountable","href":"wan24.ObjectValidation.ICountable.html","topicHref":"wan24.ObjectValidation.ICountable.html","topicUid":"wan24.ObjectValidation.ICountable"},{"name":"IItemValidationAttribute","href":"wan24.ObjectValidation.IItemValidationAttribute.html","topicHref":"wan24.ObjectValidation.IItemValidationAttribute.html","topicUid":"wan24.ObjectValidation.IItemValidationAttribute"},{"name":"ILongCountable","href":"wan24.ObjectValidation.ILongCountable.html","topicHref":"wan24.ObjectValidation.ILongCountable.html","topicUid":"wan24.ObjectValidation.ILongCountable"},{"name":"IMultipleValidations","href":"wan24.ObjectValidation.IMultipleValidations.html","topicHref":"wan24.ObjectValidation.IMultipleValidations.html","topicUid":"wan24.ObjectValidation.IMultipleValidations"},{"name":"IObjectValidatable","href":"wan24.ObjectValidation.IObjectValidatable.html","topicHref":"wan24.ObjectValidation.IObjectValidatable.html","topicUid":"wan24.ObjectValidation.IObjectValidatable"},{"name":"IValidationInfo","href":"wan24.ObjectValidation.IValidationInfo.html","topicHref":"wan24.ObjectValidation.IValidationInfo.html","topicUid":"wan24.ObjectValidation.IValidationInfo"},{"name":"IbanAttribute","href":"wan24.ObjectValidation.IbanAttribute.html","topicHref":"wan24.ObjectValidation.IbanAttribute.html","topicUid":"wan24.ObjectValidation.IbanAttribute"},{"name":"IpAttribute","href":"wan24.ObjectValidation.IpAttribute.html","topicHref":"wan24.ObjectValidation.IpAttribute.html","topicUid":"wan24.ObjectValidation.IpAttribute"},{"name":"ItemAbaRtnAttribute","href":"wan24.ObjectValidation.ItemAbaRtnAttribute.html","topicHref":"wan24.ObjectValidation.ItemAbaRtnAttribute.html","topicUid":"wan24.ObjectValidation.ItemAbaRtnAttribute"},{"name":"ItemAllowedValuesAttribute","href":"wan24.ObjectValidation.ItemAllowedValuesAttribute.html","topicHref":"wan24.ObjectValidation.ItemAllowedValuesAttribute.html","topicUid":"wan24.ObjectValidation.ItemAllowedValuesAttribute"},{"name":"ItemAmountAttribute","href":"wan24.ObjectValidation.ItemAmountAttribute.html","topicHref":"wan24.ObjectValidation.ItemAmountAttribute.html","topicUid":"wan24.ObjectValidation.ItemAmountAttribute"},{"name":"ItemBase64StringAttribute","href":"wan24.ObjectValidation.ItemBase64StringAttribute.html","topicHref":"wan24.ObjectValidation.ItemBase64StringAttribute.html","topicUid":"wan24.ObjectValidation.ItemBase64StringAttribute"},{"name":"ItemBicAttribute","href":"wan24.ObjectValidation.ItemBicAttribute.html","topicHref":"wan24.ObjectValidation.ItemBicAttribute.html","topicUid":"wan24.ObjectValidation.ItemBicAttribute"},{"name":"ItemCompanyTINAttribute","href":"wan24.ObjectValidation.ItemCompanyTINAttribute.html","topicHref":"wan24.ObjectValidation.ItemCompanyTINAttribute.html","topicUid":"wan24.ObjectValidation.ItemCompanyTINAttribute"},{"name":"ItemCompareAttribute","href":"wan24.ObjectValidation.ItemCompareAttribute.html","topicHref":"wan24.ObjectValidation.ItemCompareAttribute.html","topicUid":"wan24.ObjectValidation.ItemCompareAttribute"},{"name":"ItemCountLimitAttribute","href":"wan24.ObjectValidation.ItemCountLimitAttribute.html","topicHref":"wan24.ObjectValidation.ItemCountLimitAttribute.html","topicUid":"wan24.ObjectValidation.ItemCountLimitAttribute"},{"name":"ItemCountryAttribute","href":"wan24.ObjectValidation.ItemCountryAttribute.html","topicHref":"wan24.ObjectValidation.ItemCountryAttribute.html","topicUid":"wan24.ObjectValidation.ItemCountryAttribute"},{"name":"ItemCreditCardAttribute","href":"wan24.ObjectValidation.ItemCreditCardAttribute.html","topicHref":"wan24.ObjectValidation.ItemCreditCardAttribute.html","topicUid":"wan24.ObjectValidation.ItemCreditCardAttribute"},{"name":"ItemCurrencyAttribute","href":"wan24.ObjectValidation.ItemCurrencyAttribute.html","topicHref":"wan24.ObjectValidation.ItemCurrencyAttribute.html","topicUid":"wan24.ObjectValidation.ItemCurrencyAttribute"},{"name":"ItemCustomValidationAttribute","href":"wan24.ObjectValidation.ItemCustomValidationAttribute.html","topicHref":"wan24.ObjectValidation.ItemCustomValidationAttribute.html","topicUid":"wan24.ObjectValidation.ItemCustomValidationAttribute"},{"name":"ItemDataTypeAttribute","href":"wan24.ObjectValidation.ItemDataTypeAttribute.html","topicHref":"wan24.ObjectValidation.ItemDataTypeAttribute.html","topicUid":"wan24.ObjectValidation.ItemDataTypeAttribute"},{"name":"ItemDeniedValuesAttribute","href":"wan24.ObjectValidation.ItemDeniedValuesAttribute.html","topicHref":"wan24.ObjectValidation.ItemDeniedValuesAttribute.html","topicUid":"wan24.ObjectValidation.ItemDeniedValuesAttribute"},{"name":"ItemEmailAddressAttribute","href":"wan24.ObjectValidation.ItemEmailAddressAttribute.html","topicHref":"wan24.ObjectValidation.ItemEmailAddressAttribute.html","topicUid":"wan24.ObjectValidation.ItemEmailAddressAttribute"},{"name":"ItemEuVatIdAttribute","href":"wan24.ObjectValidation.ItemEuVatIdAttribute.html","topicHref":"wan24.ObjectValidation.ItemEuVatIdAttribute.html","topicUid":"wan24.ObjectValidation.ItemEuVatIdAttribute"},{"name":"ItemHostAttribute","href":"wan24.ObjectValidation.ItemHostAttribute.html","topicHref":"wan24.ObjectValidation.ItemHostAttribute.html","topicUid":"wan24.ObjectValidation.ItemHostAttribute"},{"name":"ItemIbanAttribute","href":"wan24.ObjectValidation.ItemIbanAttribute.html","topicHref":"wan24.ObjectValidation.ItemIbanAttribute.html","topicUid":"wan24.ObjectValidation.ItemIbanAttribute"},{"name":"ItemIpAttribute","href":"wan24.ObjectValidation.ItemIpAttribute.html","topicHref":"wan24.ObjectValidation.ItemIpAttribute.html","topicUid":"wan24.ObjectValidation.ItemIpAttribute"},{"name":"ItemLengthAttribute","href":"wan24.ObjectValidation.ItemLengthAttribute.html","topicHref":"wan24.ObjectValidation.ItemLengthAttribute.html","topicUid":"wan24.ObjectValidation.ItemLengthAttribute"},{"name":"ItemLuhnChecksumAttribute","href":"wan24.ObjectValidation.ItemLuhnChecksumAttribute.html","topicHref":"wan24.ObjectValidation.ItemLuhnChecksumAttribute.html","topicUid":"wan24.ObjectValidation.ItemLuhnChecksumAttribute"},{"name":"ItemMaxLengthAttribute","href":"wan24.ObjectValidation.ItemMaxLengthAttribute.html","topicHref":"wan24.ObjectValidation.ItemMaxLengthAttribute.html","topicUid":"wan24.ObjectValidation.ItemMaxLengthAttribute"},{"name":"ItemMinLengthAttribute","href":"wan24.ObjectValidation.ItemMinLengthAttribute.html","topicHref":"wan24.ObjectValidation.ItemMinLengthAttribute.html","topicUid":"wan24.ObjectValidation.ItemMinLengthAttribute"},{"name":"ItemNoValidationAttribute","href":"wan24.ObjectValidation.ItemNoValidationAttribute.html","topicHref":"wan24.ObjectValidation.ItemNoValidationAttribute.html","topicUid":"wan24.ObjectValidation.ItemNoValidationAttribute"},{"name":"ItemNullableAttribute","href":"wan24.ObjectValidation.ItemNullableAttribute.html","topicHref":"wan24.ObjectValidation.ItemNullableAttribute.html","topicUid":"wan24.ObjectValidation.ItemNullableAttribute"},{"name":"ItemPersonTINAttribute","href":"wan24.ObjectValidation.ItemPersonTINAttribute.html","topicHref":"wan24.ObjectValidation.ItemPersonTINAttribute.html","topicUid":"wan24.ObjectValidation.ItemPersonTINAttribute"},{"name":"ItemPhoneAttribute","href":"wan24.ObjectValidation.ItemPhoneAttribute.html","topicHref":"wan24.ObjectValidation.ItemPhoneAttribute.html","topicUid":"wan24.ObjectValidation.ItemPhoneAttribute"},{"name":"ItemRangeAttribute","href":"wan24.ObjectValidation.ItemRangeAttribute.html","topicHref":"wan24.ObjectValidation.ItemRangeAttribute.html","topicUid":"wan24.ObjectValidation.ItemRangeAttribute"},{"name":"ItemRegularExpressionAttribute","href":"wan24.ObjectValidation.ItemRegularExpressionAttribute.html","topicHref":"wan24.ObjectValidation.ItemRegularExpressionAttribute.html","topicUid":"wan24.ObjectValidation.ItemRegularExpressionAttribute"},{"name":"ItemRequiredAttribute","href":"wan24.ObjectValidation.ItemRequiredAttribute.html","topicHref":"wan24.ObjectValidation.ItemRequiredAttribute.html","topicUid":"wan24.ObjectValidation.ItemRequiredAttribute"},{"name":"ItemSSNAttribute","href":"wan24.ObjectValidation.ItemSSNAttribute.html","topicHref":"wan24.ObjectValidation.ItemSSNAttribute.html","topicUid":"wan24.ObjectValidation.ItemSSNAttribute"},{"name":"ItemStringLengthAttribute","href":"wan24.ObjectValidation.ItemStringLengthAttribute.html","topicHref":"wan24.ObjectValidation.ItemStringLengthAttribute.html","topicUid":"wan24.ObjectValidation.ItemStringLengthAttribute"},{"name":"ItemUrlAttribute","href":"wan24.ObjectValidation.ItemUrlAttribute.html","topicHref":"wan24.ObjectValidation.ItemUrlAttribute.html","topicUid":"wan24.ObjectValidation.ItemUrlAttribute"},{"name":"ItemVATAttribute","href":"wan24.ObjectValidation.ItemVATAttribute.html","topicHref":"wan24.ObjectValidation.ItemVATAttribute.html","topicUid":"wan24.ObjectValidation.ItemVATAttribute"},{"name":"ItemValidationAttribute","href":"wan24.ObjectValidation.ItemValidationAttribute.html","topicHref":"wan24.ObjectValidation.ItemValidationAttribute.html","topicUid":"wan24.ObjectValidation.ItemValidationAttribute"},{"name":"ItemValidationReferenceAttribute","href":"wan24.ObjectValidation.ItemValidationReferenceAttribute.html","topicHref":"wan24.ObjectValidation.ItemValidationReferenceAttribute.html","topicUid":"wan24.ObjectValidation.ItemValidationReferenceAttribute"},{"name":"ItemValidationTargets","href":"wan24.ObjectValidation.ItemValidationTargets.html","topicHref":"wan24.ObjectValidation.ItemValidationTargets.html","topicUid":"wan24.ObjectValidation.ItemValidationTargets"},{"name":"ItemValidationTemplateAttribute","href":"wan24.ObjectValidation.ItemValidationTemplateAttribute.html","topicHref":"wan24.ObjectValidation.ItemValidationTemplateAttribute.html","topicUid":"wan24.ObjectValidation.ItemValidationTemplateAttribute"},{"name":"ItemValidationTemplateIfAttribute","href":"wan24.ObjectValidation.ItemValidationTemplateIfAttribute.html","topicHref":"wan24.ObjectValidation.ItemValidationTemplateIfAttribute.html","topicUid":"wan24.ObjectValidation.ItemValidationTemplateIfAttribute"},{"name":"ItemXRechnungRouteAttribute","href":"wan24.ObjectValidation.ItemXRechnungRouteAttribute.html","topicHref":"wan24.ObjectValidation.ItemXRechnungRouteAttribute.html","topicUid":"wan24.ObjectValidation.ItemXRechnungRouteAttribute"},{"name":"ItemXmlAttribute","href":"wan24.ObjectValidation.ItemXmlAttribute.html","topicHref":"wan24.ObjectValidation.ItemXmlAttribute.html","topicUid":"wan24.ObjectValidation.ItemXmlAttribute"},{"name":"ItemZipCodeAttribute","href":"wan24.ObjectValidation.ItemZipCodeAttribute.html","topicHref":"wan24.ObjectValidation.ItemZipCodeAttribute.html","topicUid":"wan24.ObjectValidation.ItemZipCodeAttribute"},{"name":"LuhnChecksum","href":"wan24.ObjectValidation.LuhnChecksum.html","topicHref":"wan24.ObjectValidation.LuhnChecksum.html","topicUid":"wan24.ObjectValidation.LuhnChecksum"},{"name":"LuhnChecksumAttribute","href":"wan24.ObjectValidation.LuhnChecksumAttribute.html","topicHref":"wan24.ObjectValidation.LuhnChecksumAttribute.html","topicUid":"wan24.ObjectValidation.LuhnChecksumAttribute"},{"name":"NoValidationAttribute","href":"wan24.ObjectValidation.NoValidationAttribute.html","topicHref":"wan24.ObjectValidation.NoValidationAttribute.html","topicUid":"wan24.ObjectValidation.NoValidationAttribute"},{"name":"ObjectValidationEventArgs","href":"wan24.ObjectValidation.ObjectValidationEventArgs.html","topicHref":"wan24.ObjectValidation.ObjectValidationEventArgs.html","topicUid":"wan24.ObjectValidation.ObjectValidationEventArgs"},{"name":"ObjectValidationException","href":"wan24.ObjectValidation.ObjectValidationException.html","topicHref":"wan24.ObjectValidation.ObjectValidationException.html","topicUid":"wan24.ObjectValidation.ObjectValidationException"},{"name":"OptionsValidator","href":"wan24.ObjectValidation.OptionsValidator.html","topicHref":"wan24.ObjectValidation.OptionsValidator.html","topicUid":"wan24.ObjectValidation.OptionsValidator"},{"name":"OptionsValidator<T>","href":"wan24.ObjectValidation.OptionsValidator-1.html","topicHref":"wan24.ObjectValidation.OptionsValidator-1.html","topicUid":"wan24.ObjectValidation.OptionsValidator`1"},{"name":"ReflectionHelper","href":"wan24.ObjectValidation.ReflectionHelper.html","topicHref":"wan24.ObjectValidation.ReflectionHelper.html","topicUid":"wan24.ObjectValidation.ReflectionHelper"},{"name":"ReflectionHelper.PropertyGetter_Delegate","href":"wan24.ObjectValidation.ReflectionHelper.PropertyGetter_Delegate.html","topicHref":"wan24.ObjectValidation.ReflectionHelper.PropertyGetter_Delegate.html","topicUid":"wan24.ObjectValidation.ReflectionHelper.PropertyGetter_Delegate"},{"name":"RequiredIfAttribute","href":"wan24.ObjectValidation.RequiredIfAttribute.html","topicHref":"wan24.ObjectValidation.RequiredIfAttribute.html","topicUid":"wan24.ObjectValidation.RequiredIfAttribute"},{"name":"SwiftValidation","href":"wan24.ObjectValidation.SwiftValidation.html","topicHref":"wan24.ObjectValidation.SwiftValidation.html","topicUid":"wan24.ObjectValidation.SwiftValidation"},{"name":"ValidatableObjectBase","href":"wan24.ObjectValidation.ValidatableObjectBase.html","topicHref":"wan24.ObjectValidation.ValidatableObjectBase.html","topicUid":"wan24.ObjectValidation.ValidatableObjectBase"},{"name":"ValidatableRecordBase","href":"wan24.ObjectValidation.ValidatableRecordBase.html","topicHref":"wan24.ObjectValidation.ValidatableRecordBase.html","topicUid":"wan24.ObjectValidation.ValidatableRecordBase"},{"name":"ValidatableTypes","href":"wan24.ObjectValidation.ValidatableTypes.html","topicHref":"wan24.ObjectValidation.ValidatableTypes.html","topicUid":"wan24.ObjectValidation.ValidatableTypes"},{"name":"ValidatableTypes.TypeValidatable_Delegate","href":"wan24.ObjectValidation.ValidatableTypes.TypeValidatable_Delegate.html","topicHref":"wan24.ObjectValidation.ValidatableTypes.TypeValidatable_Delegate.html","topicUid":"wan24.ObjectValidation.ValidatableTypes.TypeValidatable_Delegate"},{"name":"ValidatableTypesEventArgs","href":"wan24.ObjectValidation.ValidatableTypesEventArgs.html","topicHref":"wan24.ObjectValidation.ValidatableTypesEventArgs.html","topicUid":"wan24.ObjectValidation.ValidatableTypesEventArgs"},{"name":"ValidateObject","href":"wan24.ObjectValidation.ValidateObject.html","topicHref":"wan24.ObjectValidation.ValidateObject.html","topicUid":"wan24.ObjectValidation.ValidateObject"},{"name":"ValidateObject.Logger_Delegate","href":"wan24.ObjectValidation.ValidateObject.Logger_Delegate.html","topicHref":"wan24.ObjectValidation.ValidateObject.Logger_Delegate.html","topicUid":"wan24.ObjectValidation.ValidateObject.Logger_Delegate"},{"name":"ValidationAttributeBase","href":"wan24.ObjectValidation.ValidationAttributeBase.html","topicHref":"wan24.ObjectValidation.ValidationAttributeBase.html","topicUid":"wan24.ObjectValidation.ValidationAttributeBase"},{"name":"ValidationAttributeBase.ErrorMessage_Delegate","href":"wan24.ObjectValidation.ValidationAttributeBase.ErrorMessage_Delegate.html","topicHref":"wan24.ObjectValidation.ValidationAttributeBase.ErrorMessage_Delegate.html","topicUid":"wan24.ObjectValidation.ValidationAttributeBase.ErrorMessage_Delegate"},{"name":"ValidationExtensions","href":"wan24.ObjectValidation.ValidationExtensions.html","topicHref":"wan24.ObjectValidation.ValidationExtensions.html","topicUid":"wan24.ObjectValidation.ValidationExtensions"},{"name":"ValidationExtensions.ObjectValidation_Delegate","href":"wan24.ObjectValidation.ValidationExtensions.ObjectValidation_Delegate.html","topicHref":"wan24.ObjectValidation.ValidationExtensions.ObjectValidation_Delegate.html","topicUid":"wan24.ObjectValidation.ValidationExtensions.ObjectValidation_Delegate"},{"name":"ValidationHelper","href":"wan24.ObjectValidation.ValidationHelper.html","topicHref":"wan24.ObjectValidation.ValidationHelper.html","topicUid":"wan24.ObjectValidation.ValidationHelper"},{"name":"ValidationReferenceAttribute","href":"wan24.ObjectValidation.ValidationReferenceAttribute.html","topicHref":"wan24.ObjectValidation.ValidationReferenceAttribute.html","topicUid":"wan24.ObjectValidation.ValidationReferenceAttribute"},{"name":"ValidationTemplateAttribute","href":"wan24.ObjectValidation.ValidationTemplateAttribute.html","topicHref":"wan24.ObjectValidation.ValidationTemplateAttribute.html","topicUid":"wan24.ObjectValidation.ValidationTemplateAttribute"},{"name":"ValidationTemplateIfAttribute","href":"wan24.ObjectValidation.ValidationTemplateIfAttribute.html","topicHref":"wan24.ObjectValidation.ValidationTemplateIfAttribute.html","topicUid":"wan24.ObjectValidation.ValidationTemplateIfAttribute"},{"name":"ValidationTemplates","href":"wan24.ObjectValidation.ValidationTemplates.html","topicHref":"wan24.ObjectValidation.ValidationTemplates.html","topicUid":"wan24.ObjectValidation.ValidationTemplates"},{"name":"ValueValidation","href":"wan24.ObjectValidation.ValueValidation.html","topicHref":"wan24.ObjectValidation.ValueValidation.html","topicUid":"wan24.ObjectValidation.ValueValidation"},{"name":"XRechnungRouteAttribute","href":"wan24.ObjectValidation.XRechnungRouteAttribute.html","topicHref":"wan24.ObjectValidation.XRechnungRouteAttribute.html","topicUid":"wan24.ObjectValidation.XRechnungRouteAttribute"},{"name":"XRechnungRouting","href":"wan24.ObjectValidation.XRechnungRouting.html","topicHref":"wan24.ObjectValidation.XRechnungRouting.html","topicUid":"wan24.ObjectValidation.XRechnungRouting"},{"name":"XmlAttribute","href":"wan24.ObjectValidation.XmlAttribute.html","topicHref":"wan24.ObjectValidation.XmlAttribute.html","topicUid":"wan24.ObjectValidation.XmlAttribute"}]}],"memberLayout":"SamePage"}
